mandelbrot_py-0.1.1.dist-info/METADATA
mandelbrot_py-0.1.1.dist-info/WHEEL
mandelbrot_rs.cpython-37m-x86_64-linux-gnu.so
mandelbrot_py-0.1.1.dist-info/RECORD
