Metadata-Version: 2.1
Name: mandelbrot_py
Version: 0.1.1
Classifier: Programming Language :: Rust
Classifier: Programming Language :: Python
Classifier: Programming Language :: Python :: 3 :: Only
Classifier: Programming Language :: Python :: 3
Classifier: Programming Language :: Python :: 3.5
Classifier: Programming Language :: Python :: 3.6
Classifier: Programming Language :: Python :: 3.7
Classifier: Programming Language :: Python :: 3.8
Classifier: Programming Language :: Python :: Implementation :: CPython
Classifier: Topic :: Software Development :: Libraries
Classifier: Topic :: Software Development :: Libraries :: Python Modules
Project-Url: https://github.com/ahoetker/mandelbrot-rs/
Summary: Python bindings to mandelbrot Rust crate
Author: Andrew Hoetker <ahoetker@me.com>
Author-Email: Andrew Hoetker <ahoetker@me.com>
Maintainer: Andrew Hoetker
Maintainer-Email: ahoetker@me.com
Requires-Python: >=3.5
